{
  "last_updated": "2025-10-29T17:53:07Z",
  "total_messages": 14,
  "by_server": {
    "build1": {
      "total_sent": 8,
      "last_message_time": 2025-10-29T17:45:28Z,
      "last_message_subject": Acknowledged libssl-dev,
      "messages_by_type": {
        "info": 7,
        "warning": 1,
        "error": 0,
        "request": 0
      }
    },
    "build2": {
      "total_sent": 6,
      "last_message_time": 2025-10-29T17:48:27Z,
      "last_message_subject": Re: coordination ping,
      "messages_by_type": {
        "info": 6,
        "warning": 0,
        "error": 0,
        "request": 0
      }
    }
  },
  "by_recipient": {
    "build1": {
      "total_received": 6,
      "unread_count": 0
    },
    "build2": {
      "total_received": 8,
      "unread_count": 1
    },
    "all": {
      "total_broadcast": 0,
      "last_broadcast_time": null
    }
  },
  "recent_activity": {
    "last_message_from": build2,
    "last_message_to": build1,
    "last_message_time": 2025-10-29T17:48:27Z,
    "last_message_type": info
  }
}
